gen_images/Dockerfile
gen_images/README.md
gen_images/__init__.py
gen_images/bailian_mcpserver.py
gen_images/docker-compose.yml.example
postgresql/README.md
postgresql/__init__.py
postgresql/pg_mcpserver.py
my_mcp_servers-0.1.7.dist-info/METADATA
my_mcp_servers-0.1.7.dist-info/WHEEL
my_mcp_servers-0.1.7.dist-info/entry_points.txt
my_mcp_servers-0.1.7.dist-info/licenses/LICENSE
my_mcp_servers-0.1.7.dist-info/RECORD
