Metadata-Version: 2.4
Name: my-mcp-servers
Version: 0.1.7
Summary: Model Context Protocol servers for PostgreSQL and Alibaba Cloud Bailian image generation
Project-URL: Homepage, https://github.com/yidasanqian/my-mcp-servers
Project-URL: Repository, https://github.com/yidasanqian/my-mcp-servers
Project-URL: Issues, https://github.com/yidasanqian/my-mcp-servers/issues
Author-email: yidasanqian <yidasanqian@gmail.com>
License: MIT
License-File: LICENSE
Keywords: alibaba-cloud,bailian,image-generation,mcp,model-context-protocol,postgresql
Classifier: Development Status :: 3 - Alpha
Classifier: Intended Audience :: Developers
Classifier: License :: OSI Approved :: MIT License
Classifier: Programming Language :: Python :: 3
Classifier: Programming Language :: Python :: 3.11
Classifier: Programming Language :: Python :: 3.12
Requires-Python: >=3.11
Requires-Dist: httpx>=0.27.0
Requires-Dist: mcp[cli]>=1.12.0
Requires-Dist: psycopg2-binary>=2.9.10
